LICENSE
MANIFEST.in
README.md
setup.py
django_gsschema.egg-info/PKG-INFO
django_gsschema.egg-info/SOURCES.txt
django_gsschema.egg-info/dependency_links.txt
django_gsschema.egg-info/not-zip-safe
django_gsschema.egg-info/requires.txt
django_gsschema.egg-info/top_level.txt
gsschema/__init__.py
gsschema/admin.py
gsschema/forms.py
gsschema/models.py
gsschema/tests.py
gsschema/urls.py
gsschema/views.py
gsschema/static/gsschema/css/style.css
gsschema/static/gsschema/js/script.js
gsschema/static/gsschema/lib/angular-cookies/js/angular-cookies.js
gsschema/static/gsschema/lib/angular/js/angular.js
gsschema/static/gsschema/lib/bootstrap/.DS_Store
gsschema/static/gsschema/lib/bootstrap/css/bootstrap-theme.css
gsschema/static/gsschema/lib/bootstrap/css/bootstrap-theme.css.map
gsschema/static/gsschema/lib/bootstrap/css/bootstrap-theme.min.css
gsschema/static/gsschema/lib/bootstrap/css/bootstrap.css
gsschema/static/gsschema/lib/bootstrap/css/bootstrap.css.map
gsschema/static/gsschema/lib/bootstrap/css/bootstrap.min.css
gsschema/static/gsschema/lib/bootstrap/fonts/glyphicons-halflings-regular.eot
gsschema/static/gsschema/lib/bootstrap/fonts/glyphicons-halflings-regular.svg
gsschema/static/gsschema/lib/bootstrap/fonts/glyphicons-halflings-regular.ttf
gsschema/static/gsschema/lib/bootstrap/fonts/glyphicons-halflings-regular.woff
gsschema/static/gsschema/lib/bootstrap/fonts/glyphicons-halflings-regular.woff2
gsschema/static/gsschema/lib/bootstrap/js/bootstrap.js
gsschema/static/gsschema/lib/bootstrap/js/bootstrap.min.js
gsschema/static/gsschema/lib/bootstrap/js/npm.js
gsschema/static/gsschema/lib/jquery/js/jquery.js
gsschema/templates/gsschema/index.html